lasuite/__init__.py
lasuite/configuration/__init__.py
lasuite/configuration/values.py
lasuite/drf/__init__.py
lasuite/drf/throttling.py
lasuite/drf/models/choices.py
lasuite/malware_detection/__init__.py
lasuite/malware_detection/admin.py
lasuite/malware_detection/enums.py
lasuite/malware_detection/exceptions.py
lasuite/malware_detection/handler.py
lasuite/malware_detection/models.py
lasuite/malware_detection/backends/__init__.py
lasuite/malware_detection/backends/base.py
lasuite/malware_detection/backends/dummy.py
lasuite/malware_detection/backends/jcop.py
lasuite/malware_detection/management/__init__.py
lasuite/malware_detection/management/commands/__init__.py
lasuite/malware_detection/management/commands/check_analysis_pending.py
lasuite/malware_detection/management/commands/reschedule_processing_analysis.py
lasuite/malware_detection/migrations/0001_initial.py
lasuite/malware_detection/migrations/0002_alter_malwaredetection_parameters.py
lasuite/malware_detection/migrations/0003_malwaredetection_error_code_and_more.py
lasuite/malware_detection/migrations/0004_malwaredetection_file_hash.py
lasuite/malware_detection/migrations/__init__.py
lasuite/malware_detection/tasks/__init__.py
lasuite/malware_detection/tasks/jcop.py
lasuite/marketing/__init__.py
lasuite/marketing/exceptions.py
lasuite/marketing/handler.py
lasuite/marketing/tasks.py
lasuite/marketing/backends/__init__.py
lasuite/marketing/backends/base.py
lasuite/marketing/backends/brevo.py
lasuite/marketing/backends/dummy.py
lasuite/oidc_login/__init__.py
lasuite/oidc_login/backends.py
lasuite/oidc_login/decorators.py
lasuite/oidc_login/enums.py
lasuite/oidc_login/middleware.py
lasuite/oidc_login/urls.py
lasuite/oidc_login/views.py
lasuite/oidc_resource_server/__init__.py
lasuite/oidc_resource_server/authentication.py
lasuite/oidc_resource_server/backend.py
lasuite/oidc_resource_server/clients.py
lasuite/oidc_resource_server/mixins.py
lasuite/oidc_resource_server/urls.py
lasuite/oidc_resource_server/utils.py
django_lasuite-0.0.23.dist-info/METADATA
django_lasuite-0.0.23.dist-info/WHEEL
django_lasuite-0.0.23.dist-info/licenses/LICENSE
django_lasuite-0.0.23.dist-info/RECORD
