Metadata-Version: 2.4
Name: django-lasuite
Version: 0.0.23
Summary: Django La Suite - A Django library
Project-URL: Homepage, https://github.com/suitenumerique/django-lasuite
Project-URL: Bug Tracker, https://github.com/suitenumerique/django-lasuite/issues
Author-email: DINUM <dev@mail.numerique.gouv.fr>
License: MIT License
License-File: LICENSE
Classifier: Development Status :: 3 - Alpha
Classifier: Framework :: Django
Classifier: Framework :: Django :: 4.2
Classifier: Framework :: Django :: 5.0
Classifier: Framework :: Django :: 5.1
Classifier: Framework :: Django :: 5.2
Classifier: Intended Audience :: Developers
Classifier: License :: OSI Approved :: MIT License
Classifier: Programming Language :: Python :: 3
Classifier: Programming Language :: Python :: 3.11
Classifier: Programming Language :: Python :: 3.12
Classifier: Programming Language :: Python :: 3.13
Classifier: Programming Language :: Python :: 3.14
Requires-Python: >=3.10
Requires-Dist: django>=5.0
Requires-Dist: djangorestframework>=3.15.2
Requires-Dist: joserfc>=1.4.0
Requires-Dist: mozilla-django-oidc>=4.0.1
Requires-Dist: pyjwt>=2.8.0
Requires-Dist: requests-toolbelt>=1.0.0
Requires-Dist: requests>=2.32.3
Provides-Extra: all
Requires-Dist: celery>=5.0; extra == 'all'
Requires-Dist: django-configurations>=2.5.1; extra == 'all'
Provides-Extra: build
Requires-Dist: setuptools; extra == 'build'
Requires-Dist: wheel; extra == 'build'
Provides-Extra: configuration
Requires-Dist: django-configurations>=2.5.1; extra == 'configuration'
Provides-Extra: dev
Requires-Dist: celery>=5.0; extra == 'dev'
Requires-Dist: django-configurations>=2.5.1; extra == 'dev'
Requires-Dist: factory-boy; extra == 'dev'
Requires-Dist: freezegun>=1.5.5; extra == 'dev'
Requires-Dist: pytest; extra == 'dev'
Requires-Dist: pytest-django; extra == 'dev'
Requires-Dist: responses; extra == 'dev'
Requires-Dist: ruff; extra == 'dev'
Provides-Extra: malware-detection
Requires-Dist: celery>=5.0; extra == 'malware-detection'
